os_dpm/__init__.py
os_dpm/constants.py
os_dpm/config/__init__.py
os_dpm/config/cfg.py
os_dpm/config/config.py
os_dpm/config/types.py
os_dpm/tests/__init__.py
os_dpm/tests/unit/__init__.py
os_dpm/tests/unit/config/__init__.py
os_dpm/tests/unit/config/test_cfg.py
os_dpm/tests/unit/config/test_config.py
os_dpm/tests/unit/config/test_types.py
os_dpm-1.1.0.dist-info/DESCRIPTION.rst
os_dpm-1.1.0.dist-info/METADATA
os_dpm-1.1.0.dist-info/RECORD
os_dpm-1.1.0.dist-info/WHEEL
os_dpm-1.1.0.dist-info/metadata.json
os_dpm-1.1.0.dist-info/pbr.json
os_dpm-1.1.0.dist-info/top_level.txt
